plotxvg/__init__.py
plotxvg/cli.py
plotxvg/plotxvg.py
plotxvg-1.1.1.dist-info/licenses/LICENSE
plotxvg-1.1.1.dist-info/METADATA
plotxvg-1.1.1.dist-info/WHEEL
plotxvg-1.1.1.dist-info/entry_points.txt
plotxvg-1.1.1.dist-info/top_level.txt
plotxvg-1.1.1.dist-info/RECORD
