Metadata-Version: 2.4
Name: plotxvg
Version: 1.1.1
Summary: Batch-generation of publication quality graphs.
Author-email: Måns Rosenbaum <mans.rosenbaum@icm.uu.se>, David van der Spoel <david.vanderspoel@icm.uu.se>
License:                     GNU GENERAL PUBLIC LICENSE
Project-URL: Homepage, https://github.com/AlexandriaChemistry/plotXVG
Project-URL: Source, https://github.com/AlexandriaChemistry/plotXVG
Project-URL: Issues, https://github.com/AlexandriaChemistry/plotXVG/issues
Requires-Python: >=3.7
License-File: LICENSE
Requires-Dist: matplotlib>=3.7.0
Requires-Dist: numpy>=1.24.1
Dynamic: license-file
